sc2api/__init__.py
sc2api/api.py
sc2api/const.py
sc2api/error.py
sc2api-0.1.3.dist-info/WHEEL
sc2api-0.1.3.dist-info/METADATA
sc2api-0.1.3.dist-info/RECORD
