Metadata-Version: 2.1
Name: sc2api
Version: 0.1.3
Summary: 
Author: Tiago Vilela
Author-email: tiagovla@gmail.com
Requires-Python: >=3.8,<4.0
Classifier: Programming Language :: Python :: 3
Classifier: Programming Language :: Python :: 3.8
Classifier: Programming Language :: Python :: 3.9
Requires-Dist: aiohttp (>=3.6.2,<4.0.0)
